{"cameraMode":{"drawMode":0,"name":"Shaded","section":"Shading Mode"},"sceneLighting":true,"audioPlay":false,"sceneViewState":{"showFog":true,"showMaterialUpdate":false,"showSkybox":true,"showFlares":true,"showImageEffects":true,"showParticleSystems":true},"in2DMode":false,"pivot":{"x":-7.034831523895264,"y":0.6544666290283203,"z":-1.162393569946289},"rotation":{"x":-0.16818232834339143,"y":0.09653130918741226,"z":-0.016551289707422258,"w":-0.980878472328186},"size":34.16532897949219,"orthographic":false}